01-accumulator/dff.v
`timescale 1ns / 1ps

module dff(input clk,input rst,input[4:0] in,output reg[4:0] out);
always@(posedge clk)
    begin
        if(rst)
            out<=5'd0;
        else
            out<=in;
    end
endmodule

01-accumulator/full_addr.v
`timescale 1ns / 1ps

module full_addr(input in1,input in2,input cin,output out,output cout);
wire g2_out,g3_out,g4_out;
xor g1(out,in1,in2,cin);
and g2(g2_out,in1,in2);
xor g3(g3_out,in1,in2);
and g4(g4_out,g3_out,cin);
or  g5(cout,g2_out,g4_out);
endmodule

01-accumulator/half_addr.v
`timescale 1ns / 1ps

module half_addr(input in1,input in2,output out,output cout);
xor g1(out,in1,in2);
and g2(cout,in1,in2);
endmodule

01-accumulator/adder_struct.v
`timescale 1ns / 1ps

module adder_struct(input[4:0] in1,input[4:0] in2,output [4:0] out);
wire c_out1,c_out2,c_out3,c_out4;
half_addr addr1(.in1(in1[0]),.in2(in2[0]),.out(out[0]),.cout(c_out1));
full_addr addr2(.in1(in1[1]),.in2(in2[1]),.cin(c_out1),.out(out[1]),.cout(c_out2));
full_addr addr3(.in1(in1[2]),.in2(in2[2]),.cin(c_out2),.out(out[2]),.cout(c_out3));
full_addr addr4(.in1(in1[3]),.in2(in2[3]),.cin(c_out3),.out(out[3]),.cout(c_out4));
full_addr addr5(.in1(in1[4]),.in2(in2[4]),.cin(c_out4),.out(out[4]),.cout());
endmodule

01-accumulator/accumulator.v
`timescale 1ns / 1ps

module accumulator(input [3:0] in, input clk,input rst, output[4:0] acc);
wire[4:0] dff_in;
wire[4:0] dff_out;
adder_struct add(.in1({1'd0,in}),.in2(dff_out),.out(dff_in));
dff mod(.clk(clk),.rst(rst),.in(dff_in),.out(dff_out));
assign acc=dff_out;
endmodule

Accumulator/test.v
`timescale 1ns / 1ps
//////////////////////////////////////////////////////////////////////////////////
// Company: 
// Engineer: 
// 
// Create Date: 14.01.2021 16:15:25
// Design Name: 
// Module Name: test
// Project Name: 
// Target Devices: 
// Tool Versions: 
// Description: 
// 
// Dependencies: 
// 
// Revision:
// Revision 0.01 - File Created
// Additional Comments:
// 
//////////////////////////////////////////////////////////////////////////////////


module test;
reg clk,rst;
reg [3:0] in;
wire [4:0] acc; 

accumulator accmod(.in(in), .clk(clk), .rst(rst), .acc(acc));

initial begin
    $dumpfile("wave.vcd");
    $dumpvars(0, test);
end

initial begin
    clk <= 1'd0;
    rst <= 1'd1;
end

always #10 clk = ~clk;

initial begin
    in <= 4'd0;
    #100 rst <= 1'd0;
    #10 in <= 4'd3;
    #20 in <= 4'd4;
    #100 $finish;
end

endmodule

Accumulator/wave.vcd
$date
	Wed Jun 17 16:58:15 2026
$end
$version
	Icarus Verilog
$end
$timescale
	1ps
$end
$scope module test $end
$var wire 5 ! acc [4:0] $end
$var reg 1 " clk $end
$var reg 4 # in [3:0] $end
$var reg 1 $ rst $end
$scope module accmod $end
$var wire 5 % acc [4:0] $end
$var wire 1 " clk $end
$var wire 4 & in [3:0] $end
$var wire 1 $ rst $end
$var wire 5 ' dff_out [4:0] $end
$var wire 5 ( dff_in [4:0] $end
$scope module add $end
$var wire 5 ) in1 [4:0] $end
$var wire 5 * out [4:0] $end
$var wire 5 + in2 [4:0] $end
$var wire 1 , c_out4 $end
$var wire 1 - c_out3 $end
$var wire 1 . c_out2 $end
$var wire 1 / c_out1 $end
$scope module addr1 $end
$var wire 1 / cout $end
$var wire 1 0 in1 $end
$var wire 1 1 in2 $end
$var wire 1 2 out $end
$upscope $end
$scope module addr2 $end
$var wire 1 / cin $end
$var wire 1 . cout $end
$var wire 1 3 g2_out $end
$var wire 1 4 g3_out $end
$var wire 1 5 g4_out $end
$var wire 1 6 in1 $end
$var wire 1 7 in2 $end
$var wire 1 8 out $end
$upscope $end
$scope module addr3 $end
$var wire 1 . cin $end
$var wire 1 - cout $end
$var wire 1 9 g2_out $end
$var wire 1 : g3_out $end
$var wire 1 ; g4_out $end
$var wire 1 < in1 $end
$var wire 1 = in2 $end
$var wire 1 > out $end
$upscope $end
$scope module addr4 $end
$var wire 1 - cin $end
$var wire 1 , cout $end
$var wire 1 ? g2_out $end
$var wire 1 @ g3_out $end
$var wire 1 A g4_out $end
$var wire 1 B in1 $end
$var wire 1 C in2 $end
$var wire 1 D out $end
$upscope $end
$scope module addr5 $end
$var wire 1 , cin $end
$var wire 1 E cout $end
$var wire 1 F g2_out $end
$var wire 1 G g3_out $end
$var wire 1 H g4_out $end
$var wire 1 I in1 $end
$var wire 1 J in2 $end
$var wire 1 K out $end
$upscope $end
$upscope $end
$scope module mod $end
$var wire 1 " clk $end
$var wire 5 L in [4:0] $end
$var wire 1 $ rst $end
$var reg 5 M out [4:0] $end
$upscope $end
$upscope $end
$upscope $end
$enddefinitions $end
$comment Show the parameter values. $end
$dumpall
$end
#0
$dumpvars
bx M
bx L
xK
xJ
0I
0H
xG
0F
0E
xD
xC
0B
0A
x@
0?
x>
x=
0<
0;
x:
09
x8
x7
06
05
x4
03
x2
x1
00
0/
0.
0-
0,
bx +
bx *
b0 )
bx (
bx '
b0 &
bx %
1$
b0 #
0"
bx !
$end
#10000
b0 (
b0 *
b0 L
0K
0G
0D
0@
0>
0:
08
04
02
0J
0C
0=
07
01
b0 !
b0 %
b0 '
b0 +
b0 M
1"
#20000
0"
#30000
1"
#40000
0"
#50000
1"
#60000
0"
#70000
1"
#80000
0"
#90000
1"
#100000
0$
0"
#110000
b11 (
b11 *
b11 L
12
18
14
10
16
b11 )
b11 #
b11 &
1"
#120000
0"
#130000
b111 (
b111 *
b111 L
1>
1:
00
06
1<
17
11
b100 )
b11 !
b11 %
b11 '
b11 +
b11 M
b100 #
b100 &
1"
#140000
0"
#150000
b1011 (
b1011 *
b1011 L
1D
1-
0>
19
0:
1=
b111 !
b111 %
b111 '
b111 +
b111 M
1"
#160000
0"
#170000
b1111 (
b1111 *
b1111 L
0-
1D
1@
1>
09
1:
1C
0=
b1011 !
b1011 %
b1011 '
b1011 +
b1011 M
1"
#180000
0"
#190000
1K
1,
b10011 (
b10011 *
b10011 L
0D
1A
1-
0>
19
0:
1=
b1111 !
b1111 %
b1111 '
b1111 +
b1111 M
1"
#200000
0"
#210000
0E
0,
b10111 (
b10111 *
b10111 L
0H
0A
0-
1K
1G
0D
0@
1>
09
1:
1J
0C
0=
b10011 !
b10011 %
b10011 '
b10011 +
b10011 M
1"
#220000
0"
#230000
b11011 (
b11011 *
b11011 L
1D
1-
0>
19
0:
1=
b10111 !
b10111 %
b10111 '
b10111 +
b10111 M
1"
